Metadata-Version: 2.1
Name: booknot
Version: 0.0.7
Summary: UNKNOWN
Home-page: UNKNOWN
License: MIT license
Platform: UNKNOWN
Classifier: Programming Language :: Python :: 3.6
Classifier: License :: OSI Approved :: MIT License
Classifier: Operating System :: OS Independent
Classifier: Intended Audience :: Developers
Classifier: Environment :: Console
Provides-Extra: dev
